pyhard/__init__.py
pyhard/__main__.py
pyhard/app.py
pyhard/base.py
pyhard/classification.py
pyhard/cli.py
pyhard/context.py
pyhard/feature_selection.py
pyhard/hpo.py
pyhard/integrator.py
pyhard/measures.py
pyhard/metrics.py
pyhard/regression.py
pyhard/structures.py
pyhard/utils.py
pyhard/validator.py
pyhard/visualization.py
pyhard/conf/config.yaml
pyhard/conf/config_old.yaml
pyhard/conf/options.json
pyhard/data/2normals/2normals.pdf
pyhard/data/2normals/coordinates.csv
pyhard/data/2normals/data.csv
pyhard/data/2normals/feature_process.csv
pyhard/data/2normals/feature_raw.csv
pyhard/data/2normals/metadata.csv
pyhard/data/2normals/options.json
pyhard/data/2normalsSd030/2normals030.pdf
pyhard/data/2normalsSd030/coordinates.csv
pyhard/data/2normalsSd030/data.csv
pyhard/data/2normalsSd030/feature_process.csv
pyhard/data/2normalsSd030/feature_raw.csv
pyhard/data/2normalsSd030/metadata.csv
pyhard/data/2normalsSd030/options.json
pyhard/data/2normalsSd045/2normals045.pdf
pyhard/data/2normalsSd045/coordinates.csv
pyhard/data/2normalsSd045/data.csv
pyhard/data/2normalsSd045/feature_process.csv
pyhard/data/2normalsSd045/feature_raw.csv
pyhard/data/2normalsSd045/metadata.csv
pyhard/data/2normalsSd045/options.json
pyhard/data/circle/circle.png
pyhard/data/circle/coordinates.csv
pyhard/data/circle/data.csv
pyhard/data/circle/feature_process.csv
pyhard/data/circle/feature_raw.csv
pyhard/data/circle/metadata.csv
pyhard/data/circle/options.json
pyhard/data/easy/coordinates.csv
pyhard/data/easy/data.csv
pyhard/data/easy/feature_process.csv
pyhard/data/easy/feature_raw_color.csv
pyhard/data/easy/metadata.csv
pyhard/data/easy/options.json
pyhard/data/easy2/coordinates.csv
pyhard/data/easy2/data.csv
pyhard/data/easy2/easy2.png
pyhard/data/easy2/metadata.csv
pyhard/data/easy2/options.json
pyhard/data/easy2/projection_matrix.csv
pyhard/data/iris/coordinates.csv
pyhard/data/iris/data.csv
pyhard/data/iris/metadata.csv
pyhard/data/iris/options.json
pyhard/data/mix/coordinates.csv
pyhard-2.2.4.dist-info/entry_points.txt
pyhard-2.2.4.dist-info/WHEEL
pyhard-2.2.4.dist-info/METADATA
pyhard-2.2.4.dist-info/RECORD
