Metadata-Version: 2.1
Name: pyhard
Version: 2.2.4
Summary: Analyze, explore and visualize instance hardness within datasets
Author-email: Pedro Paiva <paiva@ita.br>
Requires-Python: >=3.8
Classifier: Development Status :: 5 - Production/Stable
Classifier: Programming Language :: Python :: 3
Classifier: License :: OSI Approved :: MIT License
Classifier: Operating System :: OS Independent
Classifier: Topic :: Scientific/Engineering :: Artificial Intelligence
Classifier: Intended Audience :: Science/Research
Requires-Dist: pandas~=1.5.0
Requires-Dist: scikit-learn~=1.5.0
Requires-Dist: imbalanced-learn>=0.11.0
Requires-Dist: numpy~=1.23.0
Requires-Dist: PyYAML>=5.3
Requires-Dist: scipy~=1.13.0
Requires-Dist: panel~=0.14.1
Requires-Dist: param>=1.12.2, <2.0.0
Requires-Dist: bokeh>=2.4.3
Requires-Dist: holoviews>=1.15.0
Requires-Dist: matplotlib>=3.2.2
Requires-Dist: plotly>=5.9.0
Requires-Dist: plotting>=0.0.7
Requires-Dist: shapely~=1.8.0
Requires-Dist: hyperopt>=0.2.4
Requires-Dist: pyispace>=0.3.6
Requires-Dist: deprecation>=2.1.0
Requires-Dist: joblib>=1.0.0
Requires-Dist: ncafs>=0.2
Requires-Dist: typer>=0.4.1
Requires-Dist: packaging>=21.0
Requires-Dist: requests>=2.27.0
Requires-Dist: sphinx ; extra == "dev"
Requires-Dist: sphinx_rtd_theme ; extra == "dev"
Requires-Dist: pytest ; extra == "dev"
Requires-Dist: notebook>=6.4 ; extra == "dev"
Requires-Dist: jupyterlab>=3.5.3 ; extra == "dev"
Project-URL: documentation, https://ita-ml.gitlab.io/pyhard/
Project-URL: repository, https://gitlab.com/ita-ml/pyhard
Provides-Extra: dev
